pigrate
