Metadata-Version: 1.1
Name: pigrate
Version: 0.0.2
Summary: Database schema migration tool written in Python
Home-page: https://github.com/eiiches/pigrate
Author: Eiichi Sato
Author-email: sato.eiichi@gmail.com
License: UNKNOWN
Download-URL: https://github.com/eiiches/pigrate/archive/v0.0.2.tar.gz
Keywords: database,schema,migration
Platform: UNKNOWN
